{
  "slug": "chocolate-glazed-carrot-bundt-cake",
  "title": "Chocolate Glazed Carrot Bundt Cake",
  "category": "children-themed",
  "image": "/images/cakes/8dbf2a35-2133-460f-ac6f-dc912e697276.jpeg",
  "imageAlt": "Chocolate Glazed Carrot Bundt Cake",
  "flavour": "Carrot Cake",
  "description": "Moist carrot bundt cake topped with smooth white glaze, rich chocolate drizzle, and fresh berries for a delicious and elegant finish—perfect for teatime or gifting.",
  "ingredients": "Carrot sponge, cream glaze, chocolate drizzle, fresh raspberries, fresh blueberries",
  "priceFrom": 25.0,
  "featured": false,
  "published": true
}
