{
  "slug": "first-communion-pistachio-vanilla-cake",
  "title": "First Communion Pistachio Vanilla Cake",
  "category": "children-themed",
  "image": "/images/cakes/e91e646e-c289-489f-a452-e7870e554403.jpeg",
  "imageAlt": "First Communion Pistachio Vanilla Cake",
  "flavour": "Pistachio & Vanilla",
  "description": "Elegant First Communion cake featuring soft vanilla and pistachio layers, detailed lace-effect patterns, gold religious symbols, and delicate floral accents—perfect for a blessed celebration.",
  "ingredients": "Pistachio sponge, vanilla sponge, vanilla buttercream, fondant decorations, gold toppers, sugar flowers",
  "priceFrom": 145.0,
  "featured": false,
  "published": true
}
